vali/__init__.py
vali/apps.py
vali/charts.py
vali/counters.py
vali/decorator.py
vali/urls.py
vali/views.py
vali/widgets.py
vali/templatetags/__init__.py
vali/templatetags/vali_tags.py
boots_django-0.0.5.dist-info/LICENSE
boots_django-0.0.5.dist-info/METADATA
boots_django-0.0.5.dist-info/WHEEL
boots_django-0.0.5.dist-info/top_level.txt
boots_django-0.0.5.dist-info/RECORD
