Metadata-Version: 2.1
Name: boots-django
Version: 0.0.5
Summary: Pacote de layout baseado no vali
Home-page: https://github.com/MyNr/boots-django
Author: pedro
Author-email: pedroh.mix@gmail.com
License: UNKNOWN
Platform: UNKNOWN
Classifier: Programming Language :: Python :: 3
Classifier: License :: OSI Approved :: MIT License
Classifier: Operating System :: OS Independent
Requires-Python: >=3.6
